random_profile/__about__.py
random_profile/__init__.py
random_profile/api.py
random_profile/cli.py
random_profile/main.py
random_profile/utils.py
random_profile/assets/blood_types.txt
random_profile/assets/cities_name.txt
random_profile/assets/fnames_female.txt
random_profile/assets/fnames_male.txt
random_profile/assets/hair_colors.txt
random_profile/assets/job_levels.txt
random_profile/assets/job_titles.txt
random_profile/assets/lnames.txt
random_profile/assets/states_names.txt
random_profile/assets/street_names.txt
random_profile/enums/__init__.py
random_profile/enums/gender.py
random_profile-3.0.6.data/data/assets/blood_types.txt
random_profile-3.0.6.data/data/assets/cities_name.txt
random_profile-3.0.6.data/data/assets/fnames_female.txt
random_profile-3.0.6.data/data/assets/fnames_male.txt
random_profile-3.0.6.data/data/assets/hair_colors.txt
random_profile-3.0.6.data/data/assets/job_levels.txt
random_profile-3.0.6.data/data/assets/job_titles.txt
random_profile-3.0.6.data/data/assets/lnames.txt
random_profile-3.0.6.data/data/assets/states_names.txt
random_profile-3.0.6.data/data/assets/street_names.txt
random_profile-3.0.6.dist-info/licenses/LICENSE
random_profile-3.0.6.dist-info/METADATA
random_profile-3.0.6.dist-info/WHEEL
random_profile-3.0.6.dist-info/entry_points.txt
random_profile-3.0.6.dist-info/top_level.txt
random_profile-3.0.6.dist-info/RECORD
