Metadata-Version: 2.4
Name: random_profile
Version: 3.0.6
Summary: Python Module To Generate Random Profile Data
Home-page: https://github.com/Py-Contributors/RandomProfileGenerator
Author: Deepak Raj
Author-email: deepak008@live.com
Maintainer: Deepak Raj
Maintainer-email: deepak008@live.com
Project-URL: Documentation, https://pycontributors.readthedocs.io/projects/randomprofilegenerator/en/latest/
Project-URL: Source, https://github.com/Py-Contributors/RandomProfileGenerator
Project-URL: Tracker, https://github.com/Py-Contributors/RandomProfileGenerator/issues
Project-URL: Funding, https://github.com/sponsors/codePerfectPlus
Classifier: Development Status :: 5 - Production/Stable
Classifier: Programming Language :: Python :: 3
Classifier: Programming Language :: Python :: Implementation :: PyPy
Classifier: License :: OSI Approved :: MIT License
Classifier: Operating System :: OS Independent
Classifier: Topic :: Software Development :: Libraries :: Python Modules
Classifier: Topic :: Utilities
Classifier: Environment :: Plugins
License-File: LICENSE
Requires-Dist: fastapi
Requires-Dist: uvicorn
Requires-Dist: pytest
Dynamic: author
Dynamic: author-email
Dynamic: classifier
Dynamic: description
Dynamic: description-content-type
Dynamic: home-page
Dynamic: license-file
Dynamic: project-url
Dynamic: requires-dist
Dynamic: summary
